saxs_assistant/ML.py
saxs_assistant/PDDF_tools.py
saxs_assistant/__init__.py
saxs_assistant/features.py
saxs_assistant/organizer.py
saxs_assistant/rg_tools.py
saxs_assistant/runner.py
saxs_assistant/tutorial.py
saxs_assistant/models/__init__.py
saxs_assistant/models/dmax_predictor_2bundle_05262025.joblib
saxs_assistant/models/gmm_cluster_2bundle_05262025.joblib
saxs_assistant/music/Bavarian Seascape.mp3
saxs_assistant/music/Coy Koi.mp3
saxs_assistant/music/Modern Island Jam.mp3
saxs_assistant/music/Palm and Soul.mp3
saxs_assistant/plotting/__init__.py
saxs_assistant/plotting/plot_flagged.py
saxs_assistant/plotting/plot_solved_summary.py
saxs_assistant/rawutils/Profile_Loader.py
saxs_assistant/rawutils/__init__.py
saxs_assistant/rawutils/bift.py
saxs_assistant/rawutils/rawapitry.py
saxs_assistant/rawutils/sascalc.py
saxs_assistant/rawutils/sasexceptions.py
saxs_assistant/rawutils/sasm.py
saxs_assistant/utils/__init__.py
saxs_assistant/utils/helpers.py
saxs_assistant-0.1.7.dist-info/METADATA
saxs_assistant-0.1.7.dist-info/WHEEL
saxs_assistant-0.1.7.dist-info/top_level.txt
saxs_assistant-0.1.7.dist-info/RECORD
