Metadata-Version: 2.4
Name: saxs_assistant
Version: 0.1.7
Summary: SAXS Assistant: Automated analysis of SAXS data including Guinier, PDDF, and ML-based Dmax prediction
Author: Cesar Ramirez
Author-email: cr828@scarletmai.rutgers.edu
Project-URL: Tutorial, https://pypi.org/project/saxs-assistant/
Classifier: Programming Language :: Python :: 3
Classifier: License :: OSI Approved :: GNU General Public License v3 (GPLv3)
Classifier: Operating System :: OS Independent
Requires-Python: >=3.7
Requires-Dist: pandas==2.2.2
Requires-Dist: joblib==1.5.1
Requires-Dist: matplotlib==3.10.3
Requires-Dist: numba<0.62,>=0.59
Requires-Dist: numpy<3.0.0,>=2.0.0
Requires-Dist: scikit-learn==1.6.1
Requires-Dist: scipy==1.15.3
Requires-Dist: tqdm==4.67.1
Requires-Dist: openpyxl==3.1.5
Requires-Dist: pillow==11.2.1
Requires-Dist: requests<3,>=2.32
Requires-Dist: natsort
Provides-Extra: music
Requires-Dist: playsound==1.2.2; extra == "music"
Dynamic: author
Dynamic: author-email
Dynamic: classifier
Dynamic: description
Dynamic: description-content-type
Dynamic: project-url
Dynamic: provides-extra
Dynamic: requires-dist
Dynamic: requires-python
Dynamic: summary
